keyvomit/__init__.py
keyvomit/cli.py
keyvomit/core.py
keyvomit/parser.py
keyvomit-1.0.1.dist-info/licenses/LICENSE
tests/__init__.py
tests/test_copy.py
tests/test_generate.py
tests/test_parse.py
keyvomit-1.0.1.dist-info/METADATA
keyvomit-1.0.1.dist-info/WHEEL
keyvomit-1.0.1.dist-info/entry_points.txt
keyvomit-1.0.1.dist-info/top_level.txt
keyvomit-1.0.1.dist-info/RECORD
