Metadata-Version: 2.4
Name: keyvomit
Version: 1.0.1
Summary: Unhinged character sequence generator for passwords, tokens, and general chaos.
Home-page: https://github.com/mosphox/keyvomit
Author: mosphox
Author-email: mosphox@gmail.com
License: MIT
Project-URL: Source, https://github.com/mosphox/keyvomit
Project-URL: Tracker, https://github.com/mosphox/keyvomit/issues
Classifier: Programming Language :: Python :: 3
Classifier: License :: OSI Approved :: MIT License
Classifier: Operating System :: OS Independent
Classifier: Environment :: Console
Classifier: Topic :: Security :: Cryptography
Classifier: Intended Audience :: Developers
Requires-Python: >=3.7
License-File: LICENSE
Requires-Dist: pyperclip
Dynamic: author
Dynamic: author-email
Dynamic: classifier
Dynamic: description
Dynamic: description-content-type
Dynamic: home-page
Dynamic: license
Dynamic: license-file
Dynamic: project-url
Dynamic: requires-dist
Dynamic: requires-python
Dynamic: summary
